{
  "head": {
    "title": "如何通过{{ProductName}}从Excel、Word、PDF和其他文档中提取图像？",
    "description": "{{ProductFullName}} API 允许软件开发者从 {{ProductName}} 应用内的 PDF、DOC、DOCX、PPT、PPTX、XLS、XLSX 文档和电子邮件中解析和提取图像。"
  },
  "header": {
    "title": "{{ProductName}} 用于从 Excel、Word、PowerPoint、PDF 和其他文档页面解析和提取图像的 API",
    "description": "{{ProductFullName}} API 允许程序员从 PDF、DOC、DOCX、PPT、PPTX、EML、MSG、XLS、XLSX、CSV、{358 }、RTF 和 EPUB 文档或 {{ProductName}} 应用程序内的文档页面。",
    "button_label": "下载免费试用版"
  },
  "submenu": {
    "content_middle": {
      "button_text_1": "API参考",
      "button_text_2": "代码示例",
      "button_text_3": "现场演示",
      "button_text_4": "价钱"
    }
  },
  "about": {
    "title": "了解如何通过 {{ProductName}} API 从 {{EXT}} 文档或特定页面提取图像",
    "h1": "一张图片胜过一千个文字，在当今的视觉世界中，在创建引人入胜的内容时，不容忽视。图像可以成为信息交流的重要来源，也可以吸引用户的注意力。通常需要从文档、期刊或演示文稿中获取图像并在其他地方使用它们。 {{ProductFullName}} 是一个功能强大的 API，可帮助软件开发人员和程序员构建从多种文档类型中解析和提取图像或其他信息的解决方案。它还支持将图片保存为PNG、JPEG、WebP、GIF、BMP等格式。该 API 支持一些流行的文档格式，例如 PDF、Microsoft Office 格式：Word (DOC、DOCX)、PowerPoint (PPT、PPTX)、{282 }（XLS、XLSX）、LibreOffice 格式、电子邮件、电子书等等。它还支持一些与文档解析、提取纯文本和结构化文本、按关键字进行文本搜索、提取元数据或图像、容器以及附件等相关的高级功能。"
  },
  "steps": {
    "title_left": "从 {{ProductName}} 中的 {{EXT}} 中提取图像",
    "content_left": {
      "description": "[{{ProductFullName}}]({{slash_lang}}/parser/{{ProductCode}}/) 让 {{ProgLang}} 开发者只需执行几个简单的步骤即可轻松从 {{EXT}} 文件中提取图像。",
      "step_1": "实例化初始文档的 [Parser](https://reference.groupdocs.com/java/parser/com.groupdocs.parser/Parser) 对象；",
      "step_2": "调用 [getImages](https://reference.groupdocs.com/parser/java/com.groupdocs.parser/parser/#getImages--) 方法并获取图像对象集合；",
      "step_3": "检查 reader 是否不为*null*（文档支持图像提取）；",
      "step_4": "迭代集合并获取尺寸、图像类型和图像内容。"
    },
    "title_right": "了解有关图像提取的更多信息",
    "content_right": {
      "step_1": "如何从文档中提取图像",
      "step_2": "如何从文档页面中提取图像",
      "step_3": "如何从文档页面区域提取图像",
      "step_4": "如何将图像提取到文件"
    },
    "title_code": "如何使用 {{ProgLang}} 示例代码从 {{EXT}} 文件中提取图像",
    "code": {
      "header": "使用 GroupDocs.Parser API 从 {{EXT}} 文件中提取图像",
      "instance": "创建 Parser 类的实例",
      "extract": "提取图像",
      "check_null": "检查是否支持图像提取",
      "not_supported": "不支持图像提取",
      "iterate": "迭代图像",
      "print": "打印页面索引、矩形和图像类型："
    }
  },
  "more": {
    "title_left": "系统要求",
    "content_left": {
      "description": "{{ProductFullName}} 所有主要平台和操作系统均支持 API。在执行下面的代码之前，请确保您的系统上安装了以下先决条件。",
      "step_1": "操作系统：Microsoft Windows、Linux、MacOS",
      "step_2": "开发环境：{{DevEnv}}",
      "step_3": "构架",
      "step_4": "从 [{{RepoName}}]({{RepoUrl}}) 下载最新版本的 {{ProductFullName}}"
    },
    "title_right": "为什么使用{{ProductFullName}}",
    "content_right": {
      "p1": "支持从任何支持的文档中提取纯文本",
      "p2": "通过用户定义的模板解析文档",
      "p3": "全面支持结构化文本提取",
      "p4": "通过关键字和正则表达式进行文本搜索",
      "p5": "提取格式化文本、元数据、图像、容器和附件",
      "p6": "提取某些支持的文档格式的目录",
      "p7": "从 PDF 文档解析表单数据",
      "p8": "从文档中提取超链接"
    }
  },
  "demos": {
    "title": "现场演示 - 从 {{EXT}} 在线提取图像",
    "h1": "立即访问 [GroupDocs.Parser 实时演示](https://products.groupdocs.app/parser/images/{{ext}}) 网站，从 {{EXT}} 文件中提取图像。",
    "h2": "现场演示有以下好处。"
  },
  "more_formats": {
    "title": "从其他文档格式中提取图像",
    "content": "{{ProductName}} 用于文件格式和图像的文档解析和图像提取 API。提取一些流行文件格式的数据，如下所述。"
  }
}